trajectoryclusteringanalysis/__init__.py
trajectoryclusteringanalysis/__version__.py
trajectoryclusteringanalysis/logger.py
trajectoryclusteringanalysis/main.py
trajectoryclusteringanalysis/optimal_matching.c
trajectoryclusteringanalysis/optimal_matching.cp311-win_amd64.pyd
trajectoryclusteringanalysis/plotting.py
trajectoryclusteringanalysis/tca.py
trajectoryclusteringanalysis/test.py
trajectoryclusteringanalysis/utils.py
trajectoryclusteringanalysis/images/format_data.png
trajectoryclusteringanalysis/multidimensional/__init__.py
trajectoryclusteringanalysis/multidimensional/analysis.py
trajectoryclusteringanalysis/unidimensional/__init__.py
trajectoryclusteringanalysis/unidimensional/clustering.py
trajectoryclusteringanalysis-0.0.2.dist-info/licenses/LICENSE
trajectoryclusteringanalysis-0.0.2.dist-info/METADATA
trajectoryclusteringanalysis-0.0.2.dist-info/WHEEL
trajectoryclusteringanalysis-0.0.2.dist-info/top_level.txt
trajectoryclusteringanalysis-0.0.2.dist-info/RECORD
