Metadata-Version: 2.4
Name: trajectoryclusteringanalysis
Version: 0.0.2
Summary: Un package pour l’analyse des trajectoires de soins par clustering
Home-page: https://github.com/QuanTIMLab/TrajectoryClusteringAnalysis
Author: Nicolas and Ndiaga
Author-email: nicolas.grevet@univ-amu.fr
License: MIT
Project-URL: Documentation, https://github.com/QuanTIMLab/TrajectoryClusteringAnalysis
Project-URL: Code, https://github.com/QuanTIMLab/TrajectoryClusteringAnalysis
Project-URL: Bug Tracker, https://github.com/QuanTIMLab/TrajectoryClusteringAnalysis/issues
Classifier: Programming Language :: Python :: 3
Classifier: Operating System :: OS Independent
Classifier: Intended Audience :: Science/Research
Classifier: Topic :: Scientific/Engineering :: Information Analysis
Requires-Python: >=3.6
License-File: LICENSE
Requires-Dist: pandas
Requires-Dist: numpy
Requires-Dist: seaborn
Requires-Dist: matplotlib
Requires-Dist: plotly
Requires-Dist: scipy
Requires-Dist: jupyter
Requires-Dist: Levenshtein
Requires-Dist: tslearn
Requires-Dist: tqdm
Requires-Dist: h5py
Requires-Dist: numba
Requires-Dist: Cython
Requires-Dist: kmedoids
Requires-Dist: torch
Requires-Dist: SWoTTeD==1.0.2a4
Requires-Dist: omegaconf
Requires-Dist: openpyxl
Dynamic: author
Dynamic: author-email
Dynamic: classifier
Dynamic: description
Dynamic: description-content-type
Dynamic: home-page
Dynamic: license
Dynamic: license-file
Dynamic: project-url
Dynamic: requires-dist
Dynamic: requires-python
Dynamic: summary
